code_wake/__init__.py
code_wake/abstract_store.py
code_wake/config.py
code_wake/no_store.py
code_wake/pkg_meta.py
code_wake/process.py
code_wake/queue_store.py
code_wake/stack_trace.py
code_wake/utils.py
code_wake/test/__init__.py
code_wake/test/conftest.py
code_wake/test/store.py
code_wake-0.2.2.dist-info/LICENSE
code_wake-0.2.2.dist-info/METADATA
code_wake-0.2.2.dist-info/WHEEL
code_wake-0.2.2.dist-info/entry_points.txt
code_wake-0.2.2.dist-info/top_level.txt
code_wake-0.2.2.dist-info/RECORD
