Metadata-Version: 2.1
Name: code-wake
Version: 0.2.2
Summary: Running code use instrumentation aid
Home-page: https://github.com/mwri/pycodewake
Author: Michael Wright
Author-email: mjw@methodanalysis.com
License: UNKNOWN
Platform: UNKNOWN
Classifier: Programming Language :: Python :: 3
Classifier: License :: OSI Approved :: MIT License
Classifier: Operating System :: OS Independent
Requires-Python: >=3.6
Requires-Dist: bencode.py (==4.0.0)
Requires-Dist: pyyaml (==6.0)
Requires-Dist: singleton-type (==0.0.5)
Provides-Extra: dev
Requires-Dist: black (==22.3.0) ; extra == 'dev'
Requires-Dist: coverage (==6.2) ; extra == 'dev'
Requires-Dist: flask (==2.1.2) ; extra == 'dev'
Requires-Dist: isort (==5.10.1) ; extra == 'dev'
Requires-Dist: mypy (==0.961) ; extra == 'dev'
Requires-Dist: pytest-timeout (==2.1.0) ; extra == 'dev'
Requires-Dist: pytest (==7.0.1) ; extra == 'dev'
Requires-Dist: requests-flask-adapter (==0.1.0) ; extra == 'dev'
Requires-Dist: requests (==2.28.0) ; extra == 'dev'
Requires-Dist: sqlalchemy-utils (==0.38.2) ; extra == 'dev'
Requires-Dist: sqlalchemy (==1.4.39) ; extra == 'dev'
Requires-Dist: types-pyyaml (==6.0.8) ; extra == 'dev'
Requires-Dist: werkzeug (==2.1.2) ; extra == 'dev'
